nemo_automodel/__init__.py
nemo_automodel/package_info.py
nemo_automodel/_cli/app.py
nemo_automodel/_diffusers/__init__.py
nemo_automodel/_diffusers/auto_diffusion_pipeline.py
nemo_automodel/_transformers/__init__.py
nemo_automodel/_transformers/auto_model.py
nemo_automodel/_transformers/auto_tokenizer.py
nemo_automodel/_transformers/registry.py
nemo_automodel/_transformers/utils.py
nemo_automodel/components/__init__.py
nemo_automodel/components/_peft/__init__.py
nemo_automodel/components/_peft/lora.py
nemo_automodel/components/_peft/lora_kernel.py
nemo_automodel/components/_peft/module_matcher.py
nemo_automodel/components/attention/__init__.py
nemo_automodel/components/attention/flex_attention.py
nemo_automodel/components/attention/utils.py
nemo_automodel/components/checkpoint/__init__.py
nemo_automodel/components/checkpoint/_torch_backports.py
nemo_automodel/components/checkpoint/addons.py
nemo_automodel/components/checkpoint/checkpointing.py
nemo_automodel/components/checkpoint/state_dict_adapter.py
nemo_automodel/components/checkpoint/stateful_wrappers.py
nemo_automodel/components/checkpoint/_backports/__init__.py
nemo_automodel/components/checkpoint/_backports/_fsspec_filesystem.py
nemo_automodel/components/checkpoint/_backports/_version.py
nemo_automodel/components/checkpoint/_backports/consolidate_hf_safetensors.py
nemo_automodel/components/checkpoint/_backports/default_planner.py
nemo_automodel/components/checkpoint/_backports/filesystem.py
nemo_automodel/components/checkpoint/_backports/hf_storage.py
nemo_automodel/components/checkpoint/_backports/hf_utils.py
nemo_automodel/components/checkpoint/_backports/planner_helpers.py
nemo_automodel/components/config/__init__.py
nemo_automodel/components/config/_arg_parser.py
nemo_automodel/components/config/loader.py
nemo_automodel/components/datasets/__init__.py
nemo_automodel/components/datasets/utils.py
nemo_automodel/components/datasets/llm/__init__.py
nemo_automodel/components/datasets/llm/chat_dataset.py
nemo_automodel-0.2.0.dist-info/licenses/LICENSE
nemo_automodel-0.2.0.dist-info/METADATA
nemo_automodel-0.2.0.dist-info/WHEEL
nemo_automodel-0.2.0.dist-info/entry_points.txt
nemo_automodel-0.2.0.dist-info/top_level.txt
nemo_automodel-0.2.0.dist-info/RECORD
