Metadata-Version: 2.4
Name: nemo-automodel
Version: 0.2.0
Summary: DTensor-native pretraining and fine-tuning for LLMs/VLMs with day-0 Hugging Face support, GPU-acceleration, and memory efficiency.
Author-email: NVIDIA <nemo-toolkit@nvidia.com>
Maintainer-email: NVIDIA <nemo-toolkit@nvidia.com>
Project-URL: Homepage, https://docs.nvidia.com/deeplearning/nemo/user-guide/docs/en/stable/
Project-URL: Repository, https://github.com/NVIDIA/NeMo-Automodel
Project-URL: Download, https://github.com/NVIDIA/NeMo-Automodel/releases
Classifier: Development Status :: 4 - Beta
Classifier: Intended Audience :: Developers
Classifier: Intended Audience :: Science/Research
Classifier: Intended Audience :: Information Technology
Classifier: Topic :: Scientific/Engineering
Classifier: Topic :: Scientific/Engineering :: Mathematics
Classifier: Topic :: Scientific/Engineering :: Image Recognition
Classifier: Topic :: Scientific/Engineering :: Artificial Intelligence
Classifier: Topic :: Software Development :: Libraries
Classifier: Topic :: Software Development :: Libraries :: Python Modules
Classifier: Topic :: Utilities
Classifier: License :: OSI Approved :: Apache Software License
Classifier: Programming Language :: Python :: 3
Classifier: Programming Language :: Python :: 3.10
Classifier: Programming Language :: Python :: 3.11
Classifier: Programming Language :: Python :: 3.12
Classifier: Environment :: Console
Classifier: Natural Language :: English
Classifier: Operating System :: OS Independent
Requires-Python: >=3.10
License-File: LICENSE
Requires-Dist: datasets>=4.0.0
Requires-Dist: diffusers
Requires-Dist: ftfy
Requires-Dist: imageio-ffmpeg
Requires-Dist: liger-kernel>=0.5.9; platform_machine == "x86_64" and platform_system != "Darwin"
Requires-Dist: megatron-fsdp
Requires-Dist: opencv-python-headless==4.10.0.84
Requires-Dist: pybind11
Requires-Dist: pyyaml
Requires-Dist: torch<=2.9.0
Requires-Dist: torchdata
Requires-Dist: transformers<=4.57.1
Requires-Dist: wandb
Requires-Dist: torchao
Requires-Dist: mlflow
Provides-Extra: vlm
Requires-Dist: pillow; extra == "vlm"
Requires-Dist: qwen-vl-utils[decord]; (platform_machine == "x86_64" and platform_system != "Darwin") and extra == "vlm"
Requires-Dist: qwen-omni-utils; extra == "vlm"
Requires-Dist: timm==1.0.16; extra == "vlm"
Requires-Dist: backoff; extra == "vlm"
Requires-Dist: numpy; extra == "vlm"
Requires-Dist: numba; extra == "vlm"
Requires-Dist: torchcodec; (platform_machine == "x86_64" and platform_system != "Darwin") and extra == "vlm"
Requires-Dist: mistral_common[opencv]; extra == "vlm"
Provides-Extra: fa
Requires-Dist: flash-attn<=2.8.3; extra == "fa"
Provides-Extra: moe
Requires-Dist: transformer-engine[pytorch]==2.8.0; extra == "moe"
Provides-Extra: extra
Requires-Dist: flash-linear-attention; extra == "extra"
Requires-Dist: perceptron; extra == "extra"
Requires-Dist: sentencepiece; extra == "extra"
Provides-Extra: all
Requires-Dist: nemo_automodel[extra]; extra == "all"
Requires-Dist: nemo_automodel[vlm]; extra == "all"
Dynamic: license-file
